siges_sdk/__init__.py
siges_sdk/core/__init__.py
siges_sdk/core/gateway.py
siges_sdk/core/gateway_provider.py
siges_sdk/core/http_gateway.py
siges_sdk/queues/__init__.py
siges_sdk/queues/message_consumer.py
siges_sdk/queues/message_consumer_provider.py
siges_sdk/queues/message_producer.py
siges_sdk/queues/message_producer_provider.py
siges_sdk/queues/redis_message_consumer.py
siges_sdk/queues/redis_message_producer.py
siges_sdk-0.1.12.dist-info/METADATA
siges_sdk-0.1.12.dist-info/WHEEL
siges_sdk-0.1.12.dist-info/top_level.txt
siges_sdk-0.1.12.dist-info/RECORD
