Metadata-Version: 2.4
Name: siges-sdk
Version: 0.1.12
Summary: SDK para plugins de SIGES
Author: SIGES Team
License: MIT
Project-URL: Homepage, https://github.com/siges-codebase/siges-sdk
Project-URL: Bug Tracker, https://github.com/siges-codebase/siges-sdk/issues
Classifier: Programming Language :: Python :: 3
Classifier: Operating System :: OS Independent
Requires-Python: >=3.9
Requires-Dist: httpx>=0.28.1
Requires-Dist: pydantic>=2.11.5
Requires-Dist: redis>=6.2.0
Provides-Extra: dev
Requires-Dist: fastapi>=0.115.12; extra == "dev"
Requires-Dist: uvicorn>=0.22.0; extra == "dev"
Requires-Dist: pytest==7.4.3; extra == "dev"
Requires-Dist: pytest-asyncio==0.21.1; extra == "dev"
Requires-Dist: anyio==4.2.0; extra == "dev"
